huaweicloudsdkcfw/__init__.py
huaweicloudsdkcfw/v1/__init__.py
huaweicloudsdkcfw/v1/cfw_async_client.py
huaweicloudsdkcfw/v1/cfw_client.py
huaweicloudsdkcfw/v1/model/__init__.py
huaweicloudsdkcfw/v1/model/access_detail_vo.py
huaweicloudsdkcfw/v1/model/access_log_info.py
huaweicloudsdkcfw/v1/model/access_policy.py
huaweicloudsdkcfw/v1/model/access_top_member_vo.py
huaweicloudsdkcfw/v1/model/access_top_statistics_vo.py
huaweicloudsdkcfw/v1/model/access_top_vo.py
huaweicloudsdkcfw/v1/model/account_dto.py
huaweicloudsdkcfw/v1/model/account_info.py
huaweicloudsdkcfw/v1/model/account_vo.py
huaweicloudsdkcfw/v1/model/add_acl_rule_request.py
huaweicloudsdkcfw/v1/model/add_acl_rule_response.py
huaweicloudsdkcfw/v1/model/add_address_item_request.py
huaweicloudsdkcfw/v1/model/add_address_item_response.py
huaweicloudsdkcfw/v1/model/add_address_items_info_dto.py
huaweicloudsdkcfw/v1/model/add_address_items_info_dto_address_items.py
huaweicloudsdkcfw/v1/model/add_address_set_dto.py
huaweicloudsdkcfw/v1/model/add_address_set_request.py
huaweicloudsdkcfw/v1/model/add_address_set_response.py
huaweicloudsdkcfw/v1/model/add_black_white_batch_dto.py
huaweicloudsdkcfw/v1/model/add_black_white_list_batch_vo.py
huaweicloudsdkcfw/v1/model/add_black_white_list_dto.py
huaweicloudsdkcfw/v1/model/add_black_white_list_request.py
huaweicloudsdkcfw/v1/model/add_black_white_list_response.py
huaweicloudsdkcfw/v1/model/add_custom_dns_server_request.py
huaweicloudsdkcfw/v1/model/add_custom_dns_server_response.py
huaweicloudsdkcfw/v1/model/add_domain_list_dto.py
huaweicloudsdkcfw/v1/model/add_domain_set_info_dto.py
huaweicloudsdkcfw/v1/model/add_domain_set_request.py
huaweicloudsdkcfw/v1/model/add_domain_set_response.py
huaweicloudsdkcfw/v1/model/add_domains_request.py
huaweicloudsdkcfw/v1/model/add_domains_response.py
huaweicloudsdkcfw/v1/model/add_eip_alarm_whitelist_request.py
huaweicloudsdkcfw/v1/model/add_eip_alarm_whitelist_request_body.py
huaweicloudsdkcfw-3.1.184.dist-info/METADATA
huaweicloudsdkcfw-3.1.184.dist-info/WHEEL
huaweicloudsdkcfw-3.1.184.dist-info/licenses/LICENSE
huaweicloudsdkcfw-3.1.184.dist-info/RECORD
